jetblack_negotiate_stream/__init__.py
jetblack_negotiate_stream/handshake.py
jetblack_negotiate_stream/negotiate_stream.py
jetblack_negotiate_stream/negotiate_stream_async.py
jetblack_negotiate_stream/negotiate_stream_async_alt.py
jetblack_negotiate_stream/py.typed
jetblack_negotiate_stream/stream.py
jetblack_negotiate_stream/stream_wrapper.py
jetblack_negotiate_stream-0.2.2.dist-info/WHEEL
jetblack_negotiate_stream-0.2.2.dist-info/METADATA
jetblack_negotiate_stream-0.2.2.dist-info/RECORD
