Metadata-Version: 2.1
Name: jetblack-negotiate-stream
Version: 0.2.2
Summary: A python client for .Net NegotiateStream
Home-page: https://github.com/rob-blackbourn/jetblack-negotiate-stream
License: Apache-2.0
Author: Rob Blackbourn
Author-email: rob.blackbourn@gmail.com
Requires-Python: >=3.8,<4.0
Classifier: License :: OSI Approved :: Apache Software License
Classifier: Programming Language :: Python :: 3
Classifier: Programming Language :: Python :: 3.10
Classifier: Programming Language :: Python :: 3.8
Classifier: Programming Language :: Python :: 3.9
Requires-Dist: pyspnego (>=0.7,<0.8)
Project-URL: Repository, https://github.com/rob-blackbourn/jetblack-negotiate-stream
